odoo/addons/web_widget_image_webcam/README.rst
odoo/addons/web_widget_image_webcam/__init__.py
odoo/addons/web_widget_image_webcam/__manifest__.py
odoo/addons/web_widget_image_webcam/i18n/es.po
odoo/addons/web_widget_image_webcam/i18n/it.po
odoo/addons/web_widget_image_webcam/i18n/web_widget_image_webcam.pot
odoo/addons/web_widget_image_webcam/models/__init__.py
odoo/addons/web_widget_image_webcam/models/ir_config_parameter.py
odoo/addons/web_widget_image_webcam/readme/CONFIGURE.rst
odoo/addons/web_widget_image_webcam/readme/CONTRIBUTORS.rst
odoo/addons/web_widget_image_webcam/readme/DESCRIPTION.rst
odoo/addons/web_widget_image_webcam/static/description/icon.png
odoo/addons/web_widget_image_webcam/static/description/index.html
odoo/addons/web_widget_image_webcam/static/src/css/web_widget_image_webcam.css
odoo/addons/web_widget_image_webcam/static/src/img/webcam_placeholder.png
odoo/addons/web_widget_image_webcam/static/src/js/webcam_widget.js
odoo/addons/web_widget_image_webcam/static/src/lib/webcam.js
odoo/addons/web_widget_image_webcam/static/src/lib/webcam.swf
odoo/addons/web_widget_image_webcam/static/src/xml/web_widget_image_webcam.xml
odoo_addon_web_widget_image_webcam-16.0.1.0.0.6.dist-info/METADATA
odoo_addon_web_widget_image_webcam-16.0.1.0.0.6.dist-info/WHEEL
odoo_addon_web_widget_image_webcam-16.0.1.0.0.6.dist-info/top_level.txt
odoo_addon_web_widget_image_webcam-16.0.1.0.0.6.dist-info/RECORD
