Metadata-Version: 2.1
Name: odoo-addon-web-widget-image-webcam
Version: 16.0.1.0.0.6
Summary: Allows to take image with WebCam
Home-page: https://github.com/OCA/web
Author: Tech Receptives, Kaushal Prajapati, Odoo Community Association (OCA)
Author-email: support@odoo-community.org
License: LGPL-3
Platform: UNKNOWN
Classifier: Programming Language :: Python
Classifier: Framework :: Odoo
Classifier: Framework :: Odoo :: 16.0
Classifier: License :: OSI Approved :: GNU Lesser General Public License v3 (LGPLv3)
Requires-Python: >=3.10
Requires-Dist: odoo <16.1dev,>=16.0a
